score.distlock-0.2.5-py3.4-nspkg.pth
score/distlock/__init__.py
score/distlock/_init.py
score.distlock-0.2.5.dist-info/DESCRIPTION.rst
score.distlock-0.2.5.dist-info/METADATA
score.distlock-0.2.5.dist-info/RECORD
score.distlock-0.2.5.dist-info/WHEEL
score.distlock-0.2.5.dist-info/metadata.json
score.distlock-0.2.5.dist-info/namespace_packages.txt
score.distlock-0.2.5.dist-info/top_level.txt
